goose_checker/chains.py
goose_checker/cli.py
goose_checker/context.py
goose_checker/diff.py
goose_checker/goose_ascii.py
goose_checker/models.py
goose_checker/prompts.py
goose_checker/response_schema.py
goose_checker-0.0.12.dist-info/LICENSE
goose_checker-0.0.12.dist-info/METADATA
goose_checker-0.0.12.dist-info/WHEEL
goose_checker-0.0.12.dist-info/entry_points.txt
goose_checker-0.0.12.dist-info/RECORD
